[
  {
    "referrer": "Google",
    "count": 776,
    "uniques": 173
  },
  {
    "referrer": "reddit.com",
    "count": 357,
    "uniques": 192
  },
  {
    "referrer": "github.com",
    "count": 129,
    "uniques": 37
  },
  {
    "referrer": "Bing",
    "count": 57,
    "uniques": 11
  },
  {
    "referrer": "community.spiceworks.com",
    "count": 38,
    "uniques": 11
  },
  {
    "referrer": "DuckDuckGo",
    "count": 34,
    "uniques": 3
  },
  {
    "referrer": "explicitconsulting.at",
    "count": 23,
    "uniques": 6
  },
  {
    "referrer": "statics.teams.cdn.office.net",
    "count": 19,
    "uniques": 7
  },
  {
    "referrer": "1itservices.sharepoint.com",
    "count": 17,
    "uniques": 2
  },
  {
    "referrer": "lm.facebook.com",
    "count": 8,
    "uniques": 6
  }
]